Galfgets/AuxiliarFunctions.py
Galfgets/DataAnalysisTools.py
Galfgets/DataStructureTools.py
Galfgets/GraphicsTools.py
Galfgets/RegularExpressions.py
Galfgets/SystemTools.py
Galfgets/__init__.py
Galfgets-0.2.4.3.dist-info/METADATA
Galfgets-0.2.4.3.dist-info/WHEEL
Galfgets-0.2.4.3.dist-info/top_level.txt
Galfgets-0.2.4.3.dist-info/RECORD
